qudotpy-1.0.0-nspkg.pth
qudotpy/algorithms.py
qudotpy/errors.py
qudotpy/hamiltonians.py
qudotpy/qudot.py
qudotpy/qulib.py
qudotpy/test_qudotpy.py
qudotpy/utils.py
qudotpy-1.0.0.data/data/LICENSE.txt
qudotpy-1.0.0.data/data/README.md
qudotpy-1.0.0.dist-info/DESCRIPTION.rst
qudotpy-1.0.0.dist-info/METADATA
qudotpy-1.0.0.dist-info/RECORD
qudotpy-1.0.0.dist-info/WHEEL
qudotpy-1.0.0.dist-info/metadata.json
qudotpy-1.0.0.dist-info/namespace_packages.txt
qudotpy-1.0.0.dist-info/top_level.txt
