Metadata-Version: 2.0
Name: qudotpy
Version: 1.0.0
Summary: A quantum computing library written in Python. Can be used to emulate quantum circuits.
Home-page: https://github.com/psakkaris/qudotpy
Author: psakkaris
Author-email: psakkaris@gmail.com
License: Apache License 2.0
Keywords: quantum qubit computation emulation qft shor grover
Platform: any
Classifier: Development Status :: 5 - Production/Stable
Classifier: Intended Audience :: Developers
Classifier: License :: OSI Approved :: Apache Software License
Classifier: Operating System :: OS Independent
Classifier: Programming Language :: Python
Classifier: Topic :: Scientific/Engineering
Classifier: Topic :: Scientific/Engineering :: Physics
Classifier: Topic :: Scientific/Engineering :: Mathematics
Provides: qudotpy
Requires-Python: >=3.6, < 4
Requires-Dist: numpy
